odoo8_addon_project_issue_code-8.0.1.0.0.99.dev14-nspkg.pth
odoo_addons/project_issue_code/README.rst
odoo_addons/project_issue_code/__init__.py
odoo_addons/project_issue_code/__openerp__.py
odoo_addons/project_issue_code/hooks.py
odoo_addons/project_issue_code/data/project_issue_sequence.xml
odoo_addons/project_issue_code/i18n/bg.po
odoo_addons/project_issue_code/i18n/de.po
odoo_addons/project_issue_code/i18n/es.po
odoo_addons/project_issue_code/i18n/fr.po
odoo_addons/project_issue_code/i18n/project_issue_code.pot
odoo_addons/project_issue_code/i18n/pt.po
odoo_addons/project_issue_code/i18n/pt_BR.po
odoo_addons/project_issue_code/i18n/pt_PT.po
odoo_addons/project_issue_code/i18n/sk.po
odoo_addons/project_issue_code/i18n/sl.po
odoo_addons/project_issue_code/i18n/zh_CN.po
odoo_addons/project_issue_code/models/__init__.py
odoo_addons/project_issue_code/models/project_issue.py
odoo_addons/project_issue_code/static/description/icon.png
odoo_addons/project_issue_code/views/project_issue_view.xml
odoo8_addon_project_issue_code-8.0.1.0.0.99.dev14.dist-info/METADATA
odoo8_addon_project_issue_code-8.0.1.0.0.99.dev14.dist-info/WHEEL
odoo8_addon_project_issue_code-8.0.1.0.0.99.dev14.dist-info/namespace_packages.txt
odoo8_addon_project_issue_code-8.0.1.0.0.99.dev14.dist-info/top_level.txt
odoo8_addon_project_issue_code-8.0.1.0.0.99.dev14.dist-info/RECORD
