Metadata-Version: 2.1
Name: odoo8-addon-project-issue-code
Version: 8.0.1.0.0.99.dev14
Summary: Adding Field Code For Project Issue
Home-page: http://github.com/mikevhe18
Author: Michael Viriyananda,Odoo Community Association (OCA)
Author-email: support@odoo-community.org
License: AGPL-3
Platform: UNKNOWN
Classifier: Programming Language :: Python
Classifier: Framework :: Odoo
Classifier: License :: OSI Approved :: GNU Affero General Public License v3
Requires-Python: ~=2.7
Requires-Dist: odoo (<9.0a,>=8.0a)
